{
  "epoch": 3,
  "converged": true,
  "max_delta": 0.0,
  "cell_deltas": {
    "add_norm1": 0.0,
    "add_norm2": 0.0,
    "alignment_group": 0.0,
    "bbox_pruning_group": 0.0,
    "coarse_dom_tree": 0.0,
    "code_linking": 0.0,
    "content_align": 0.0,
    "dec_conv1": 0.0,
    "dec_conv2": 0.0,
    "dec_upsamp": 0.0,
    "decoder": 0.0,
    "display_errors": 0.0,
    "empty_elements": 0.0,
    "enc_conv1": 0.0,
    "enc_conv2": 0.0,
    "enc_pool": 0.0,
    "encoder": 0.0,
    "ffn": 0.0,
    "final_css": 0.0,
    "final_html": 0.0,
    "heuristic_rules": 0.0,
    "hidden_elements": 0.0,
    "hidden_states": 0.0,
    "input": 0.0,
    "input_embed": 0.0,
    "input_image": 0.0,
    "integrated_code": 0.0,
    "json_output": 0.0,
    "latent": 0.0,
    "leaf_extraction": 0.0,
    "local_code_gen": 0.0,
    "local_images": 0.0,
    "loss_training": 0.0,
    "mllm_code_agent": 0.0,
    "mllm_style_agent": 0.0,
    "next_token_prediction": 0.0,
    "noise_detection": 0.0,
    "noise_types": 0.0,
    "nonleaf_styling": 0.0,
    "output": 0.0,
    "output_group": 0.0,
    "patch_division": 0.0,
    "pos_encode": 0.0,
    "pruned_dataset": 0.0,
    "ram_resource": 0.0,
    "rendered_webpage": 0.0,
    "resolution_handling": 0.0,
    "self_attn": 0.0,
    "softmax_layer": 0.0,
    "stage1_group": 0.0,
    "stage2_group": 0.0,
    "structure_align": 0.0,
    "structure_model": 0.0,
    "style_align": 0.0,
    "transformer_decoder": 0.0,
    "vision2ui_dataset": 0.0,
    "vit_encoder": 0.0,
    "weight_matrix": 0.0
  },
  "diverged": false,
  "threshold": 0.5
}