{
  "cell_id": "noise_types",
  "tick": 5,
  "timestamp_ms": 1782802152584,
  "transform": {
    "x": 610.091,
    "y": 666.34,
    "scale": 1.03,
    "rotation": -0.0235
  },
  "sdf": {
    "type": "metaball",
    "base_radius": 59.664,
    "lobes": [
      {
        "angle": -0.0497,
        "distance": 44.497,
        "radius": 38.531
      }
    ],
    "noise_amplitude": 0.0511,
    "noise_frequency": 4.056
  },
  "surface": {
    "albedo": [
      0.151,
      0.597,
      0.853
    ],
    "roughness": 0.507,
    "metallic": 0.109,
    "opacity": 0.8438,
    "glow_color": [
      0.2,
      0.7,
      1.0
    ],
    "glow_intensity": 0.783
  },
  "membrane": {
    "thickness": 2.486,
    "wobble_amplitude": 0.0151,
    "wobble_frequency": 1.5,
    "permeability_visual": 0.5
  },
  "pseudopods": [
    {
      "target_cell": "hidden_elements",
      "length": 60.0,
      "width": 12.0,
      "curl": -0.03253625544108934
    }
  ],
  "internal_motion": {
    "cytoplasm_flow_angle": -0.1974,
    "cytoplasm_flow_speed": 0.3,
    "organelle_drift": 0.0203
  }
}