{
  "cell_id": "self_attn",
  "tick": 19,
  "timestamp_ms": 1782869805135,
  "transform": {
    "x": 51.184,
    "y": 53.726,
    "scale": 1.03,
    "rotation": -0.0287
  },
  "sdf": {
    "type": "metaball",
    "base_radius": 15.68,
    "lobes": [
      {
        "angle": 0.0922,
        "distance": 11.525,
        "radius": 9.957
      }
    ],
    "noise_amplitude": 0.054,
    "noise_frequency": 4.2
  },
  "surface": {
    "albedo": [
      0.12,
      0.58,
      0.82
    ],
    "roughness": 0.525,
    "metallic": 0.05,
    "opacity": 0.6475,
    "glow_color": [
      0.2,
      0.7,
      1.0
    ],
    "glow_intensity": 0.74
  },
  "membrane": {
    "thickness": 2.45,
    "wobble_amplitude": 0.0155,
    "wobble_frequency": 1.5,
    "permeability_visual": 0.5
  },
  "pseudopods": [],
  "internal_motion": {
    "cytoplasm_flow_angle": -0.1974,
    "cytoplasm_flow_speed": 0.3,
    "organelle_drift": 0.021
  }
}